src/__init__.py
src/logging/__init__.py
src/logging/action_logging.py
src/logging/system_logging.py
bluepi_jupiter-0.1.0.dist-info/WHEEL
bluepi_jupiter-0.1.0.dist-info/METADATA
bluepi_jupiter-0.1.0.dist-info/RECORD
