Metadata-Version: 2.1
Name: bluepi-jupiter
Version: 0.1.0
Summary: Share python packages internally
Author: Ake - Akekatharn Booncharoensukpisarn
Author-email: akekatharn.b@bluepi.co.th
Requires-Python: >=3.8,<4.0
Classifier: Programming Language :: Python :: 3
Classifier: Programming Language :: Python :: 3.8
Classifier: Programming Language :: Python :: 3.9
